[
    {
        "序号": 1,
        "名称": "可口可乐咯",
        "职位": "长老",
        "部落等级": 234,
        "第一次攻击": "第 1 次进攻",
        "第一次攻击详情": "2. 九纹鱼 83% ★★",
        "第二次攻击": "第 2 次进攻",
        "第二次攻击详情": "4. 此去清风来 100% ★★★",
        "获得的星": 3,
        "评价": ""
    },
    {
        "序号": 2,
        "名称": "锤飒",
        "职位": "副首领",
        "部落等级": 208,
        "第一次攻击": "第 1 次进攻",
        "第一次攻击详情": "3. 黑䰞丶紫閣 78% ★★",
        "第二次攻击": "第 2 次进攻",
        "第二次攻击详情": "7. 不是山谷 80% ★",
        "获得的星": 3,
        "评价": "饼干皮卡没什么问题"
    },
    {
        "序号": 3,
        "名称": "天帝",
        "职位": "副首领",
        "部落等级": 225,
        "第一次攻击": "第 1 次进攻",
        "第一次攻击详情": "6.CZYILY 68% ★",
        "第二次攻击": "第 2 次进攻",
        "第二次攻击详情": "10. 星谶 100% ★★",
        "获得的星": 2,
        "评价": "超弓寄了"
    },
    {
        "序号": 4,
        "名称": "留白",
        "职位": "副首领",
        "部落等级": 203,
        "第一次攻击": "第 1 次进攻",
        "第一次攻击详情": "4. 此去清风来 85% ★★",
        "第二次攻击": "第 2 次进攻",
        "第二次攻击详情": "6.CZYILY 0% ★",
        "获得的星": 2,
        "评价": "掉线"
    },
    {
        "序号": 5,
        "名称": "星星 Vitas",
        "职位": "副首领",
        "部落等级": 186,
        "第一次攻击": "第 1 次进攻",
        "第一次攻击详情": "6.CZYILY 100% ★★★",
        "第二次攻击": "第 2 次进攻",
        "第二次攻击详情": "7. 不是山谷 100% ★★★",
        "获得的星": 4,
        "评价": ""
    },
    {
        "序号": 6,
        "名称": "石村",
        "职位": "副首领",
        "部落等级": 171,
        "第一次攻击": "第 1 次进攻",
        "第一次攻击详情": "5. 杰米哥 82% ★★",
        "第二次攻击": "第 2 次进攻",
        "第二次攻击详情": "11. 美女腿上坐 100% ★★★",
        "获得的星": 5,
        "评价": ""
    },
    {
        "序号": 7,
        "名称": "sleep",
        "职位": "副首领",
        "部落等级": 192,
        "第一次攻击": "第 1 次进攻",
        "第一次攻击详情": "9.The 荒天帝 82% ★★",
        "第二次攻击": "第 2 次进攻",
        "第二次攻击详情": "8.TT 77% ★★",
        "获得的星": 4,
        "评价": ""
    },
    {
        "序号": 8,
        "名称": "常胜将军",
        "职位": "长老",
        "部落等级": 216,
        "第一次攻击": "第 1 次进攻",
        "第一次攻击详情": "9.The 荒天帝 58% ★★",
        "第二次攻击": "第 2 次进攻",
        "第二次攻击详情": "未使用",
        "获得的星": 0,
        "评价": ""
    },
    {
        "序号": 9,
        "名称": "Sg-Group 吴彦祖",
        "职位": "副首领",
        "部落等级": 243,
        "第一次攻击": "第 1 次进攻",
        "第一次攻击详情": "10. 星谶 98% ★★",
        "第二次攻击": "第 2 次进攻",
        "第二次攻击详情": "1. 唔该走葱 52% ★★",
        "获得的星": 2,
        "评价": ""
    },
    {
        "序号": 10,
        "名称": "剑神重生",
        "职位": "副首领",
        "部落等级": 178,
        "第一次攻击": "第 1 次进攻",
        "第一次攻击详情": "10. 星谶 82% ★★",
        "第二次攻击": "第 2 次进攻",
        "第二次攻击详情": "20. 故事 100% ★★★",
        "获得的星": 5,
        "评价": ""
    },
    {
        "序号": 11,
        "名称": "顺其自然",
        "职位": "副首领",
        "部落等级": 211,
        "第一次攻击": "第 1 次进攻",
        "第一次攻击详情": "3. 黑䰞丶紫閣 61% ★★",
        "第二次攻击": "第 2 次进攻",
        "第二次攻击详情": "4. 此去清风来 52% ★★",
        "获得的星": 0,
        "评价": ""
    },
    {
        "序号": 12,
        "名称": "不吃香菜呜呜",
        "职位": "副首领",
        "部落等级": 156,
        "第一次攻击": "第 1 次进攻",
        "第一次攻击详情": "未使用",
        "第二次攻击": "第 2 次进攻",
        "第二次攻击详情": "未使用",
        "获得的星": 0,
        "评价": ""
    },
    {
        "序号": 13,
        "名称": "清风 / 于世",
        "职位": "副首领",
        "部落等级": 177,
        "第一次攻击": "第 1 次进攻",
        "第一次攻击详情": "12. 召唤师峡谷 100% ★★★",
        "第二次攻击": "第 2 次进攻",
        "第二次攻击详情": "9.The 荒天帝 72% ★★",
        "获得的星": 1,
        "评价": ""
    },
    {
        "序号": 14,
        "名称": "海风掀起爱意",
        "职位": "副首领",
        "部落等级": 215,
        "第一次攻击": "第 1 次进攻",
        "第一次攻击详情": "24.huoshe 100% ★★",
        "第二次攻击": "第 2 次进攻",
        "第二次攻击详情": "12. 召唤师峡谷 48% ",
        "获得的星": 1,
        "评价": "垃圾流派垃圾装备"
    },
    {
        "序号": 15,
        "名称": "RSHUO",
        "职位": "副首领",
        "部落等级": 210,
        "第一次攻击": "第 1 次进攻",
        "第一次攻击详情": "12. 召唤师峡谷 99% ★★",
        "第二次攻击": "第 2 次进攻",
        "第二次攻击详情": "14. 玲珑 100% ★★★",
        "获得的星": 3,
        "评价": ""
    },
    {
        "序号": 16,
        "名称": "萨乌森 桑尼号 风",
        "职位": "长老",
        "部落等级": 199,
        "第一次攻击": "第 1 次进攻",
        "第一次攻击详情": "13.Legend 丿狂乱 100% ★★★",
        "第二次攻击": "第 2 次进攻",
        "第二次攻击详情": "8.TT 100% ★★★",
        "获得的星": 2,
        "评价": ""
    },
    {
        "序号": 17,
        "名称": "繁花漂流落潇潇",
        "职位": "副首领",
        "部落等级": 173,
        "第一次攻击": "第 1 次进攻",
        "第一次攻击详情": "17. 叶修 100% ★★★",
        "第二次攻击": "第 2 次进攻",
        "第二次攻击详情": "15. 哈哈哈哈 100% ★★★",
        "获得的星": 6,
        "评价": ""
    },
    {
        "序号": 18,
        "名称": "煞長嘯",
        "职位": "副首领",
        "部落等级": 192,
        "第一次攻击": "第 1 次进攻",
        "第一次攻击详情": "14. 玲珑 89% ★★",
        "第二次攻击": "第 2 次进攻",
        "第二次攻击详情": "13.Legend 丿狂乱 72% ★★",
        "获得的星": 4,
        "评价": ""
    },
    {
        "序号": 19,
        "名称": "葱葱拉满",
        "职位": "副首领",
        "部落等级": 168,
        "第一次攻击": "第 1 次进攻",
        "第一次攻击详情": "16.LegeNd 丿千残 100% ★★★",
        "第二次攻击": "第 2 次进攻",
        "第二次攻击详情": "18. 湊慕 100% ★★★",
        "获得的星": 6,
        "评价": ""
    },
    {
        "序号": 20,
        "名称": "阿琪哥哥",
        "职位": "副首领",
        "部落等级": 164,
        "第一次攻击": "第 1 次进攻",
        "第一次攻击详情": "23. 忘情 100% ★★★",
        "第二次攻击": "第 2 次进攻",
        "第二次攻击详情": "21. 情缘 100% ★★★",
        "获得的星": 6,
        "评价": ""
    },
    {
        "序号": 21,
        "名称": "夜色如酒～导人醉～",
        "职位": "副首领",
        "部落等级": 162,
        "第一次攻击": "第 1 次进攻",
        "第一次攻击详情": "未使用",
        "第二次攻击": "第 2 次进攻",
        "第二次攻击详情": "未使用",
        "获得的星": 0,
        "评价": ""
    },
    {
        "序号": 22,
        "名称": "XbeR",
        "职位": "长老",
        "部落等级": 135,
        "第一次攻击": "第 1 次进攻",
        "第一次攻击详情": "9.The 荒天帝 61% ★★",
        "第二次攻击": "第 2 次进攻",
        "第二次攻击详情": "21. 情缘 100% ★★★",
        "获得的星": 0,
        "评价": ""
    },
    {
        "序号": 23,
        "名称": "爱吃蛋炒饭",
        "职位": "副首领",
        "部落等级": 137,
        "第一次攻击": "第 1 次进攻",
        "第一次攻击详情": "22. 无名村庄 100% ★★★",
        "第二次攻击": "第 2 次进攻",
        "第二次攻击详情": "19. 薜鱼修 100% ★★★",
        "获得的星": 6,
        "评价": ""
    },
    {
        "序号": 24,
        "名称": "林七夜",
        "职位": "副首领",
        "部落等级": 128,
        "第一次攻击": "第 1 次进攻",
        "第一次攻击详情": "24.huoshe 93% ★★",
        "第二次攻击": "第 2 次进攻",
        "第二次攻击详情": "25. 你这脑子 100% ★★★",
        "获得的星": 5,
        "评价": ""
    },
    {
        "序号": 25,
        "名称": "狂飙",
        "职位": "长老",
        "部落等级": 117,
        "第一次攻击": "第 1 次进攻",
        "第一次攻击详情": "未使用",
        "第二次攻击": "第 2 次进攻",
        "第二次攻击详情": "未使用",
        "获得的星": 0,
        "评价": ""
    }
]